sec_ai/__init__.py
sec_ai/hello.py
sec_ai/py.typed
sec_ai-0.7.0.post24.dist-info/LICENSE
sec_ai-0.7.0.post24.dist-info/METADATA
sec_ai-0.7.0.post24.dist-info/WHEEL
sec_ai-0.7.0.post24.dist-info/RECORD
