Metadata-Version: 2.1
Name: sec-ai
Version: 0.7.0.post24
Summary: A comprehensive open-source toolkit for AI-powered analysis and interpretation of SEC EDGAR filings, providing valuable insights for investors, fintech developers, and researchers.
Home-page: https://github.com/alphanome-ai/sec-ai
License: MIT
Author: Alphanome.AI
Author-email: info@alphanome.ai
Requires-Python: >=3.9, !=2.7.*, !=3.0.*, !=3.1.*, !=3.2.*, !=3.3.*, !=3.4.*, !=3.5.*, !=3.6.*, !=3.7.*, !=3.8.*
Classifier: Development Status :: 2 - Pre-Alpha
Classifier: Intended Audience :: Developers
Classifier: Intended Audience :: Financial and Insurance Industry
Classifier: Intended Audience :: Science/Research
Classifier: License :: OSI Approved :: MIT License
Classifier: Natural Language :: English
Classifier: Operating System :: OS Independent
Classifier: Programming Language :: Python :: 3
Classifier: Programming Language :: Python :: 3.9
Classifier: Programming Language :: Python :: 3.10
Classifier: Programming Language :: Python :: 3.11
Classifier: Topic :: Office/Business :: Financial
Classifier: Topic :: Scientific/Engineering :: Artificial Intelligence
Classifier: Topic :: Scientific/Engineering :: Information Analysis
Classifier: Topic :: Software Development :: Libraries :: Python Modules
Requires-Dist: python-dotenv (>=1.0.0,<2.0.0)
Requires-Dist: sec-parser (>=0.27.0,<0.28.0)
Project-URL: Repository, https://github.com/alphanome-ai/sec-ai
